_pyndeval.cpython-37m-i386-linux-gnu.so
pyndeval-0.0.6.dist-info/METADATA
pyndeval-0.0.6.dist-info/RECORD
pyndeval-0.0.6.dist-info/WHEEL
pyndeval-0.0.6.dist-info/top_level.txt
pyndeval/__init__.py
