Metadata-Version: 2.1
Name: pyndeval
Version: 0.0.6
Summary: Interface to ndeval.c
Home-page: https://github.com/seanmacavaney/pyndeval
Author: Sean MacAvaney
Author-email: sean.macavaney@glasgow.ac.uk
Classifier: License :: OSI Approved :: MIT License
Requires-Python: >=3.6
